CODATA/__init__.py
CODATA-1.2.dist-info/LICENSE
CODATA-1.2.dist-info/METADATA
CODATA-1.2.dist-info/WHEEL
CODATA-1.2.dist-info/top_level.txt
CODATA-1.2.dist-info/RECORD
