Metadata-Version: 2.1
Name: CODATA
Version: 1.2
Summary: All CODATA constants with units, uncertainty and
Home-page: https://github.com/JelleWestra/CODATA
Author: Jelle Westra
Author-email: jelwestra@gmail.com
License: UNKNOWN
Platform: UNKNOWN
Classifier: Programming Language :: Python :: 3
Classifier: License :: OSI Approved :: MIT License
Classifier: Operating System :: OS Independent
